Metadata-Version: 1.0
Name: django-infinite-pagination
Version: 1.0
Summary: Infinite pagination for Django.
Home-page: https://github.com/nigma/django-infinite-pagination
Author: Filip Wasilewski
Author-email: en@ig.ma
License: BSD
Download-URL: https://github.com/nigma/django-infinite-pagination/zipball/master
Platform: UNKNOWN
Classifier: Development Status :: 4 - Beta
Classifier: Environment :: Web Environment
Classifier: Framework :: Django
Classifier: Intended Audience :: Developers
Classifier: License :: OSI Approved :: BSD License
Classifier: Operating System :: OS Independent
Classifier: Programming Language :: Python
Classifier: Programming Language :: Python :: 2.5
Classifier: Programming Language :: Python :: 2.6
Classifier: Programming Language :: Python :: 2.7
Classifier: Topic :: Software Development :: Libraries :: Python Modules
